muffin_dogpilecache
