Metadata-Version: 1.1
Name: muffin-dogpilecache
Version: 0.0.2
Summary: UNKNOWN
Home-page: https://github.com/abnerpc/muffin-dogpilecache
Author: Abner Campanha
Author-email: abnerpc@gmail.com
License: MIT
Keywords: asyncio,aiohttp,muffin,dogpile,cache
Platform: Any
Classifier: Development Status :: 4 - Beta
Classifier: Intended Audience :: Developers
Classifier: License :: OSI Approved :: MIT License
Classifier: Natural Language :: English
Classifier: Operating System :: OS Independent
Classifier: Programming Language :: Python :: 3
Classifier: Programming Language :: Python
Classifier: Topic :: Software Development :: Libraries :: Python Modules
Classifier: Topic :: Software Development :: Testing
Classifier: Topic :: Utilities
